Epoch_Helpers-1.3.dist-info/DESCRIPTION.rst
Epoch_Helpers-1.3.dist-info/METADATA
Epoch_Helpers-1.3.dist-info/RECORD
Epoch_Helpers-1.3.dist-info/WHEEL
Epoch_Helpers-1.3.dist-info/entry_points.txt
Epoch_Helpers-1.3.dist-info/metadata.json
Epoch_Helpers-1.3.dist-info/top_level.txt
epoch_helpers/__init__.py
epoch_helpers/days_since_epoch.py
epoch_helpers/months_since_epoch.py
epoch_helpers/test/__init__.py
epoch_helpers/test/days_since_epoch_test.py
epoch_helpers/test/months_since_epoch_test.py
