Metadata-Version: 2.0
Name: Epoch-Helpers
Version: 1.3
Summary: Helpers for comparing dates with January 1st, 1970
Home-page: https://github.com/cbrentharris/epoch-helpers.git
Author: Christopher Harris
Author-email: cbrentharris@gmail.com
License: UNKNOWN
Platform: UNKNOWN
